hashfields/__init__.py
hashfields/csv.py
hashfields/hashing.py
hashfields/main.py
hashfields-2023.9.1.dist-info/LICENSE
hashfields-2023.9.1.dist-info/METADATA
hashfields-2023.9.1.dist-info/WHEEL
hashfields-2023.9.1.dist-info/entry_points.txt
hashfields-2023.9.1.dist-info/top_level.txt
hashfields-2023.9.1.dist-info/RECORD
