Metadata-Version: 2.1
Name: hashfields
Version: 2023.9.1
Summary: Selectively hash, drop, or keep fields from a flat file (e.g. CSV).
License: Apache License
Project-URL: Code, https://github.com/cal-itp/hashfields
Project-URL: Documentation, https://docs.calitp.org/hashfields
Project-URL: Issues, https://github.com/cal-itp/hashfields/issues
Classifier: Programming Language :: Python :: 3 :: Only
Requires-Python: >=3.11
License-File: LICENSE
Requires-Dist: pandas ==2.1.0
Provides-Extra: dev
Requires-Dist: black ; extra == 'dev'
Requires-Dist: flake8 ; extra == 'dev'
Requires-Dist: pre-commit ; extra == 'dev'
Provides-Extra: dist
Requires-Dist: build ; extra == 'dist'
Requires-Dist: pyinstaller ; extra == 'dist'
Requires-Dist: twine ; extra == 'dist'
Provides-Extra: test
Requires-Dist: coverage ; extra == 'test'
Requires-Dist: pytest ; extra == 'test'
Requires-Dist: pytest-mock ; extra == 'test'
